{
    "experiment_config": {
        "experiment_id": "experiment_6c",
        "rl_agent": "actor_critic",
        "rl_variant": "quantum",
        "qpc_architecture": "ReUploadingPQC",
        "n_qubits": 4,
        "n_layers": 3,
        "n_actions": 2,
        "n_episodes": 3000,
        "batch_size": 16,
        "gamma": 1,
        "learning_rate": 0.01,
        "max_steps_per_episode": 10000,
        "exploration_strategy": "epsilon_greedy",
        "epsilon_decay": "exponential",
        "rerun_id": 5,
        "seed": 539,
        "env_name": "CartPole-v1"
    },
    "other_parameters": {
        "num_actor_observables": 1,
        "num_critic_observables": 2,
        "num_actor_qubits": 4,
        "num_critic_qubits": 4,
        "actor_qubits": "[cirq.GridQubit(0, 0), cirq.GridQubit(0, 1), cirq.GridQubit(0, 2), cirq.GridQubit(0, 3)]",
        "critic_qubits": "[cirq.GridQubit(0, 0), cirq.GridQubit(0, 1), cirq.GridQubit(0, 2), cirq.GridQubit(0, 3)]",
        "actor_ops": "[cirq.Z(cirq.GridQubit(0, 0)), cirq.Z(cirq.GridQubit(0, 1)), cirq.Z(cirq.GridQubit(0, 2)), cirq.Z(cirq.GridQubit(0, 3))]",
        "critic_ops": "[cirq.Z(cirq.GridQubit(0, 0)), cirq.Z(cirq.GridQubit(0, 1)), cirq.Z(cirq.GridQubit(0, 2)), cirq.Z(cirq.GridQubit(0, 3))]",
        "actor_observables": "[(cirq.Z(cirq.GridQubit(0, 0))*cirq.Z(cirq.GridQubit(0, 1))*cirq.Z(cirq.GridQubit(0, 2))*cirq.Z(cirq.GridQubit(0, 3)))]",
        "critic_observables": "[(cirq.Z(cirq.GridQubit(0, 0))*cirq.Z(cirq.GridQubit(0, 1))), (cirq.Z(cirq.GridQubit(0, 2))*cirq.Z(cirq.GridQubit(0, 3)))]"
    },
    "model_details": {
        "input_shape": [
            [
                null,
                4
            ],
            [
                null,
                4
            ]
        ],
        "output_shape": [
            [
                null,
                2
            ],
            [
                null,
                2
            ]
        ],
        "trainable_params": [
            62,
            62
        ]
    },
    "metrics": {
        "episode_reward_history": [
            26.0,
            21.0,
            49.0,
            11.0,
            27.0,
            18.0,
            29.0,
            26.0,
            37.0,
            20.0,
            23.0,
            20.0,
            23.0,
            24.0,
            14.0,
            53.0,
            30.0,
            11.0,
            18.0,
            36.0,
            22.0,
            25.0,
            36.0,
            33.0,
            24.0,
            11.0,
            24.0,
            13.0,
            25.0,
            36.0,
            41.0,
            38.0,
            16.0,
            58.0,
            62.0,
            12.0,
            32.0,
            24.0,
            19.0,
            34.0,
            62.0,
            39.0,
            69.0,
            127.0,
            66.0,
            16.0,
            26.0,
            12.0,
            19.0,
            78.0,
            37.0,
            37.0,
            30.0,
            14.0,
            20.0,
            17.0,
            22.0,
            65.0,
            46.0,
            26.0,
            66.0,
            22.0,
            31.0,
            82.0,
            25.0,
            25.0,
            18.0,
            38.0,
            8.0,
            67.0,
            28.0,
            48.0,
            92.0,
            65.0,
            56.0,
            22.0,
            55.0,
            61.0,
            85.0,
            45.0,
            35.0,
            44.0,
            47.0,
            13.0,
            22.0,
            19.0,
            66.0,
            50.0,
            49.0,
            19.0,
            23.0,
            34.0,
            41.0,
            50.0,
            46.0,
            47.0,
            13.0,
            54.0,
            92.0,
            35.0,
            40.0,
            68.0,
            81.0,
            44.0,
            36.0,
            38.0,
            27.0,
            65.0,
            25.0,
            64.0,
            99.0,
            61.0,
            31.0,
            37.0,
            74.0,
            52.0,
            53.0,
            23.0,
            26.0,
            57.0,
            80.0,
            37.0,
            214.0,
            69.0,
            116.0,
            39.0,
            132.0,
            77.0,
            60.0,
            54.0,
            83.0,
            133.0,
            49.0,
            59.0,
            27.0,
            96.0,
            65.0,
            84.0,
            66.0,
            97.0,
            73.0,
            60.0,
            125.0,
            77.0,
            85.0,
            73.0,
            99.0,
            54.0,
            31.0,
            121.0,
            164.0,
            117.0,
            224.0,
            182.0,
            112.0,
            37.0,
            130.0,
            60.0,
            61.0,
            173.0,
            103.0,
            26.0,
            170.0,
            117.0,
            102.0,
            48.0,
            138.0,
            79.0,
            112.0,
            61.0,
            91.0,
            76.0,
            61.0,
            50.0,
            43.0,
            162.0,
            147.0,
            77.0,
            100.0,
            61.0,
            155.0,
            84.0,
            58.0,
            195.0,
            202.0,
            66.0,
            206.0,
            175.0,
            53.0,
            140.0,
            115.0,
            97.0,
            90.0,
            105.0,
            21.0,
            132.0,
            47.0,
            173.0,
            185.0,
            72.0,
            273.0,
            101.0,
            117.0,
            169.0,
            42.0,
            164.0,
            103.0,
            85.0,
            61.0,
            75.0,
            79.0,
            24.0,
            27.0,
            92.0,
            32.0,
            77.0,
            53.0,
            68.0,
            81.0,
            60.0,
            71.0,
            137.0,
            52.0,
            73.0,
            173.0,
            78.0,
            117.0,
            183.0,
            206.0,
            243.0,
            135.0,
            86.0,
            128.0,
            68.0,
            141.0,
            92.0,
            52.0,
            64.0,
            110.0,
            105.0,
            111.0,
            52.0,
            75.0,
            44.0,
            24.0,
            169.0,
            27.0,
            111.0,
            123.0,
            72.0,
            49.0,
            115.0,
            114.0,
            89.0,
            101.0,
            84.0,
            84.0,
            184.0,
            97.0,
            67.0,
            106.0,
            164.0,
            118.0,
            56.0,
            196.0,
            105.0,
            86.0,
            86.0,
            108.0,
            87.0,
            92.0,
            60.0,
            142.0,
            117.0,
            61.0,
            38.0,
            151.0,
            109.0,
            213.0,
            68.0,
            75.0,
            143.0,
            157.0,
            74.0,
            74.0,
            53.0,
            94.0,
            192.0,
            108.0,
            82.0,
            158.0,
            100.0,
            109.0,
            69.0,
            30.0,
            42.0,
            68.0,
            37.0,
            38.0,
            110.0,
            127.0,
            120.0,
            125.0,
            115.0,
            134.0,
            83.0,
            86.0,
            172.0,
            84.0,
            170.0,
            56.0,
            138.0,
            93.0,
            224.0,
            139.0,
            146.0,
            82.0,
            134.0,
            150.0,
            94.0,
            112.0,
            137.0,
            190.0,
            104.0,
            194.0,
            76.0,
            87.0,
            104.0,
            42.0,
            161.0,
            78.0,
            177.0,
            120.0,
            117.0,
            164.0,
            260.0,
            11.0,
            121.0,
            171.0,
            113.0,
            115.0,
            99.0,
            99.0,
            93.0,
            105.0,
            155.0,
            117.0,
            204.0,
            175.0,
            187.0,
            172.0,
            113.0,
            204.0,
            179.0,
            140.0,
            241.0,
            64.0,
            95.0,
            112.0,
            65.0,
            55.0,
            282.0,
            40.0,
            116.0,
            60.0,
            97.0,
            123.0,
            134.0,
            93.0,
            82.0,
            25.0,
            123.0,
            90.0,
            41.0,
            176.0,
            80.0,
            129.0,
            95.0,
            178.0,
            83.0,
            61.0,
            139.0,
            89.0,
            113.0,
            128.0,
            42.0,
            120.0,
            132.0,
            112.0,
            184.0,
            46.0,
            92.0,
            60.0,
            53.0,
            62.0,
            249.0,
            134.0,
            108.0,
            190.0,
            103.0,
            105.0,
            164.0,
            65.0,
            217.0,
            184.0,
            71.0,
            83.0,
            64.0,
            137.0,
            89.0,
            274.0,
            108.0,
            283.0,
            86.0,
            210.0,
            148.0,
            98.0,
            92.0,
            59.0,
            203.0,
            81.0,
            84.0,
            175.0,
            205.0,
            229.0,
            227.0,
            150.0,
            149.0,
            154.0,
            224.0,
            343.0,
            139.0,
            182.0,
            107.0,
            244.0,
            130.0,
            150.0,
            141.0,
            118.0,
            102.0,
            146.0,
            245.0,
            109.0,
            154.0,
            216.0,
            168.0,
            268.0,
            240.0,
            240.0,
            229.0,
            237.0,
            177.0,
            137.0,
            358.0,
            47.0,
            66.0,
            222.0,
            81.0,
            117.0,
            94.0,
            56.0,
            74.0,
            68.0,
            48.0,
            112.0,
            19.0,
            77.0,
            65.0,
            80.0,
            75.0,
            80.0,
            75.0,
            65.0,
            37.0,
            65.0,
            61.0,
            89.0,
            85.0,
            63.0,
            156.0,
            355.0,
            104.0,
            96.0,
            108.0,
            92.0,
            47.0,
            98.0,
            105.0,
            54.0,
            98.0,
            96.0,
            163.0,
            79.0,
            42.0,
            92.0,
            77.0,
            116.0,
            57.0,
            198.0,
            122.0,
            71.0,
            49.0,
            82.0,
            191.0,
            127.0,
            149.0,
            190.0,
            249.0,
            327.0,
            218.0,
            148.0,
            356.0,
            98.0,
            39.0,
            55.0,
            57.0,
            51.0,
            26.0,
            95.0,
            106.0,
            85.0,
            47.0,
            105.0,
            38.0,
            16.0,
            32.0,
            37.0,
            17.0,
            30.0,
            45.0,
            43.0,
            18.0,
            88.0,
            32.0,
            84.0,
            112.0,
            71.0,
            129.0,
            55.0,
            88.0,
            85.0,
            132.0,
            156.0,
            83.0,
            327.0,
            123.0,
            83.0,
            214.0,
            177.0,
            113.0,
            89.0,
            240.0,
            203.0,
            127.0,
            112.0,
            183.0,
            131.0,
            115.0,
            120.0,
            107.0,
            85.0,
            69.0,
            56.0,
            74.0,
            86.0,
            32.0,
            112.0,
            108.0,
            138.0,
            111.0,
            108.0,
            86.0,
            139.0,
            174.0,
            356.0,
            92.0,
            142.0,
            173.0,
            128.0,
            82.0,
            309.0,
            98.0,
            346.0,
            332.0,
            237.0,
            130.0,
            98.0,
            158.0,
            201.0,
            129.0,
            113.0,
            113.0,
            97.0,
            98.0,
            94.0,
            39.0,
            59.0,
            99.0,
            117.0,
            100.0,
            132.0,
            84.0,
            93.0,
            150.0,
            120.0,
            120.0,
            147.0,
            167.0,
            115.0,
            82.0,
            157.0,
            123.0,
            177.0,
            205.0,
            307.0,
            101.0,
            231.0,
            173.0,
            128.0,
            161.0,
            202.0,
            113.0,
            213.0,
            312.0,
            228.0,
            147.0,
            145.0,
            217.0,
            92.0,
            96.0,
            317.0,
            183.0,
            206.0,
            294.0,
            222.0,
            188.0,
            382.0,
            320.0,
            184.0,
            500.0,
            363.0,
            500.0,
            359.0,
            444.0,
            417.0,
            220.0,
            284.0,
            446.0,
            240.0,
            107.0,
            69.0,
            143.0,
            206.0,
            252.0,
            500.0,
            388.0,
            178.0,
            116.0,
            129.0,
            143.0,
            292.0,
            171.0,
            136.0,
            139.0,
            59.0,
            141.0,
            131.0,
            113.0,
            144.0,
            195.0,
            148.0,
            170.0,
            105.0,
            146.0,
            169.0,
            119.0,
            156.0,
            175.0,
            148.0,
            130.0,
            123.0,
            104.0,
            181.0,
            170.0,
            191.0,
            181.0,
            138.0,
            122.0,
            177.0,
            128.0,
            263.0,
            135.0,
            113.0,
            175.0,
            64.0,
            285.0,
            274.0,
            215.0,
            228.0,
            217.0,
            303.0,
            307.0,
            129.0,
            89.0,
            275.0,
            286.0,
            312.0,
            243.0,
            273.0,
            235.0,
            344.0,
            240.0,
            136.0,
            237.0,
            210.0,
            389.0,
            311.0,
            212.0,
            218.0,
            500.0,
            194.0,
            351.0,
            382.0,
            449.0,
            500.0,
            163.0,
            159.0,
            228.0,
            315.0,
            173.0,
            135.0,
            168.0,
            158.0,
            156.0,
            269.0,
            221.0,
            195.0,
            151.0,
            171.0,
            500.0,
            500.0,
            500.0,
            500.0,
            353.0,
            500.0,
            500.0,
            143.0,
            500.0,
            222.0,
            171.0,
            235.0,
            223.0,
            247.0,
            144.0,
            307.0,
            500.0,
            292.0,
            242.0,
            111.0,
            253.0,
            256.0,
            259.0,
            145.0,
            305.0,
            356.0,
            413.0,
            500.0,
            213.0,
            318.0,
            500.0,
            147.0,
            500.0,
            500.0,
            386.0,
            339.0,
            398.0,
            500.0,
            500.0,
            500.0,
            500.0,
            500.0,
            500.0,
            500.0,
            353.0,
            500.0,
            89.0,
            448.0,
            296.0,
            349.0,
            500.0,
            500.0,
            500.0,
            500.0,
            500.0,
            500.0,
            181.0,
            331.0,
            144.0,
            218.0,
            165.0,
            161.0,
            184.0,
            122.0,
            87.0,
            115.0,
            102.0,
            57.0,
            117.0,
            33.0,
            37.0,
            105.0,
            50.0,
            103.0,
            106.0,
            34.0,
            124.0,
            118.0,
            38.0,
            115.0,
            118.0,
            110.0,
            115.0,
            113.0,
            88.0,
            116.0,
            128.0,
            99.0,
            141.0,
            162.0,
            148.0,
            304.0,
            152.0,
            209.0,
            118.0,
            185.0,
            168.0,
            220.0,
            500.0,
            500.0,
            95.0,
            347.0,
            270.0,
            177.0,
            234.0,
            415.0,
            137.0,
            233.0,
            500.0,
            366.0,
            477.0,
            500.0,
            108.0,
            317.0,
            500.0,
            500.0,
            405.0,
            500.0,
            500.0,
            500.0,
            500.0,
            150.0,
            180.0,
            340.0,
            129.0,
            311.0,
            184.0,
            269.0,
            46.0,
            146.0,
            92.0,
            95.0,
            192.0,
            141.0,
            162.0,
            141.0,
            250.0,
            131.0,
            100.0,
            171.0,
            177.0,
            136.0,
            137.0,
            140.0,
            55.0,
            75.0,
            41.0,
            100.0,
            79.0,
            131.0,
            93.0,
            132.0,
            120.0,
            124.0,
            145.0,
            132.0,
            113.0,
            124.0,
            69.0,
            157.0,
            119.0,
            124.0,
            153.0,
            173.0,
            148.0,
            148.0,
            171.0,
            161.0,
            157.0,
            169.0,
            188.0,
            158.0,
            197.0,
            210.0,
            445.0,
            319.0,
            500.0,
            495.0,
            500.0,
            420.0,
            438.0,
            354.0,
            305.0,
            369.0,
            372.0,
            347.0,
            286.0,
            272.0,
            182.0,
            243.0,
            149.0,
            206.0,
            230.0,
            230.0,
            224.0,
            259.0,
            175.0,
            156.0,
            230.0,
            171.0,
            204.0,
            168.0,
            142.0,
            128.0,
            140.0,
            145.0,
            137.0,
            135.0,
            105.0,
            129.0,
            161.0,
            128.0,
            122.0,
            128.0,
            46.0,
            113.0,
            139.0,
            114.0,
            156.0,
            153.0,
            172.0,
            144.0,
            98.0,
            176.0,
            194.0,
            188.0,
            166.0,
            208.0,
            181.0,
            210.0,
            212.0,
            202.0,
            188.0,
            179.0,
            195.0,
            197.0,
            181.0,
            189.0,
            231.0,
            215.0,
            216.0,
            217.0,
            241.0,
            202.0,
            258.0,
            218.0,
            235.0,
            326.0,
            263.0,
            245.0,
            373.0,
            328.0,
            270.0,
            353.0,
            293.0,
            500.0,
            500.0,
            227.0,
            288.0,
            384.0,
            308.0,
            293.0,
            324.0,
            281.0,
            338.0,
            285.0,
            366.0,
            264.0,
            284.0,
            281.0,
            329.0,
            208.0,
            249.0,
            187.0,
            217.0,
            268.0,
            217.0,
            280.0,
            297.0,
            220.0,
            252.0,
            256.0,
            243.0,
            296.0,
            219.0,
            317.0,
            454.0,
            438.0,
            332.0,
            500.0,
            500.0,
            500.0,
            500.0,
            500.0,
            500.0,
            259.0,
            331.0,
            388.0,
            148.0,
            167.0,
            315.0,
            148.0,
            311.0,
            124.0,
            152.0,
            381.0,
            287.0,
            235.0,
            500.0,
            343.0,
            181.0,
            280.0,
            500.0,
            122.0,
            328.0,
            298.0,
            260.0,
            300.0,
            128.0,
            190.0,
            157.0,
            403.0,
            311.0,
            500.0,
            483.0,
            250.0,
            500.0,
            500.0,
            500.0,
            500.0,
            500.0,
            500.0,
            500.0,
            500.0,
            500.0,
            500.0,
            500.0,
            500.0,
            500.0,
            500.0,
            500.0
        ],
        "episode_length_history": [
            26,
            21,
            49,
            11,
            27,
            18,
            29,
            26,
            37,
            20,
            23,
            20,
            23,
            24,
            14,
            53,
            30,
            11,
            18,
            36,
            22,
            25,
            36,
            33,
            24,
            11,
            24,
            13,
            25,
            36,
            41,
            38,
            16,
            58,
            62,
            12,
            32,
            24,
            19,
            34,
            62,
            39,
            69,
            127,
            66,
            16,
            26,
            12,
            19,
            78,
            37,
            37,
            30,
            14,
            20,
            17,
            22,
            65,
            46,
            26,
            66,
            22,
            31,
            82,
            25,
            25,
            18,
            38,
            8,
            67,
            28,
            48,
            92,
            65,
            56,
            22,
            55,
            61,
            85,
            45,
            35,
            44,
            47,
            13,
            22,
            19,
            66,
            50,
            49,
            19,
            23,
            34,
            41,
            50,
            46,
            47,
            13,
            54,
            92,
            35,
            40,
            68,
            81,
            44,
            36,
            38,
            27,
            65,
            25,
            64,
            99,
            61,
            31,
            37,
            74,
            52,
            53,
            23,
            26,
            57,
            80,
            37,
            214,
            69,
            116,
            39,
            132,
            77,
            60,
            54,
            83,
            133,
            49,
            59,
            27,
            96,
            65,
            84,
            66,
            97,
            73,
            60,
            125,
            77,
            85,
            73,
            99,
            54,
            31,
            121,
            164,
            117,
            224,
            182,
            112,
            37,
            130,
            60,
            61,
            173,
            103,
            26,
            170,
            117,
            102,
            48,
            138,
            79,
            112,
            61,
            91,
            76,
            61,
            50,
            43,
            162,
            147,
            77,
            100,
            61,
            155,
            84,
            58,
            195,
            202,
            66,
            206,
            175,
            53,
            140,
            115,
            97,
            90,
            105,
            21,
            132,
            47,
            173,
            185,
            72,
            273,
            101,
            117,
            169,
            42,
            164,
            103,
            85,
            61,
            75,
            79,
            24,
            27,
            92,
            32,
            77,
            53,
            68,
            81,
            60,
            71,
            137,
            52,
            73,
            173,
            78,
            117,
            183,
            206,
            243,
            135,
            86,
            128,
            68,
            141,
            92,
            52,
            64,
            110,
            105,
            111,
            52,
            75,
            44,
            24,
            169,
            27,
            111,
            123,
            72,
            49,
            115,
            114,
            89,
            101,
            84,
            84,
            184,
            97,
            67,
            106,
            164,
            118,
            56,
            196,
            105,
            86,
            86,
            108,
            87,
            92,
            60,
            142,
            117,
            61,
            38,
            151,
            109,
            213,
            68,
            75,
            143,
            157,
            74,
            74,
            53,
            94,
            192,
            108,
            82,
            158,
            100,
            109,
            69,
            30,
            42,
            68,
            37,
            38,
            110,
            127,
            120,
            125,
            115,
            134,
            83,
            86,
            172,
            84,
            170,
            56,
            138,
            93,
            224,
            139,
            146,
            82,
            134,
            150,
            94,
            112,
            137,
            190,
            104,
            194,
            76,
            87,
            104,
            42,
            161,
            78,
            177,
            120,
            117,
            164,
            260,
            11,
            121,
            171,
            113,
            115,
            99,
            99,
            93,
            105,
            155,
            117,
            204,
            175,
            187,
            172,
            113,
            204,
            179,
            140,
            241,
            64,
            95,
            112,
            65,
            55,
            282,
            40,
            116,
            60,
            97,
            123,
            134,
            93,
            82,
            25,
            123,
            90,
            41,
            176,
            80,
            129,
            95,
            178,
            83,
            61,
            139,
            89,
            113,
            128,
            42,
            120,
            132,
            112,
            184,
            46,
            92,
            60,
            53,
            62,
            249,
            134,
            108,
            190,
            103,
            105,
            164,
            65,
            217,
            184,
            71,
            83,
            64,
            137,
            89,
            274,
            108,
            283,
            86,
            210,
            148,
            98,
            92,
            59,
            203,
            81,
            84,
            175,
            205,
            229,
            227,
            150,
            149,
            154,
            224,
            343,
            139,
            182,
            107,
            244,
            130,
            150,
            141,
            118,
            102,
            146,
            245,
            109,
            154,
            216,
            168,
            268,
            240,
            240,
            229,
            237,
            177,
            137,
            358,
            47,
            66,
            222,
            81,
            117,
            94,
            56,
            74,
            68,
            48,
            112,
            19,
            77,
            65,
            80,
            75,
            80,
            75,
            65,
            37,
            65,
            61,
            89,
            85,
            63,
            156,
            355,
            104,
            96,
            108,
            92,
            47,
            98,
            105,
            54,
            98,
            96,
            163,
            79,
            42,
            92,
            77,
            116,
            57,
            198,
            122,
            71,
            49,
            82,
            191,
            127,
            149,
            190,
            249,
            327,
            218,
            148,
            356,
            98,
            39,
            55,
            57,
            51,
            26,
            95,
            106,
            85,
            47,
            105,
            38,
            16,
            32,
            37,
            17,
            30,
            45,
            43,
            18,
            88,
            32,
            84,
            112,
            71,
            129,
            55,
            88,
            85,
            132,
            156,
            83,
            327,
            123,
            83,
            214,
            177,
            113,
            89,
            240,
            203,
            127,
            112,
            183,
            131,
            115,
            120,
            107,
            85,
            69,
            56,
            74,
            86,
            32,
            112,
            108,
            138,
            111,
            108,
            86,
            139,
            174,
            356,
            92,
            142,
            173,
            128,
            82,
            309,
            98,
            346,
            332,
            237,
            130,
            98,
            158,
            201,
            129,
            113,
            113,
            97,
            98,
            94,
            39,
            59,
            99,
            117,
            100,
            132,
            84,
            93,
            150,
            120,
            120,
            147,
            167,
            115,
            82,
            157,
            123,
            177,
            205,
            307,
            101,
            231,
            173,
            128,
            161,
            202,
            113,
            213,
            312,
            228,
            147,
            145,
            217,
            92,
            96,
            317,
            183,
            206,
            294,
            222,
            188,
            382,
            320,
            184,
            500,
            363,
            500,
            359,
            444,
            417,
            220,
            284,
            446,
            240,
            107,
            69,
            143,
            206,
            252,
            500,
            388,
            178,
            116,
            129,
            143,
            292,
            171,
            136,
            139,
            59,
            141,
            131,
            113,
            144,
            195,
            148,
            170,
            105,
            146,
            169,
            119,
            156,
            175,
            148,
            130,
            123,
            104,
            181,
            170,
            191,
            181,
            138,
            122,
            177,
            128,
            263,
            135,
            113,
            175,
            64,
            285,
            274,
            215,
            228,
            217,
            303,
            307,
            129,
            89,
            275,
            286,
            312,
            243,
            273,
            235,
            344,
            240,
            136,
            237,
            210,
            389,
            311,
            212,
            218,
            500,
            194,
            351,
            382,
            449,
            500,
            163,
            159,
            228,
            315,
            173,
            135,
            168,
            158,
            156,
            269,
            221,
            195,
            151,
            171,
            500,
            500,
            500,
            500,
            353,
            500,
            500,
            143,
            500,
            222,
            171,
            235,
            223,
            247,
            144,
            307,
            500,
            292,
            242,
            111,
            253,
            256,
            259,
            145,
            305,
            356,
            413,
            500,
            213,
            318,
            500,
            147,
            500,
            500,
            386,
            339,
            398,
            500,
            500,
            500,
            500,
            500,
            500,
            500,
            353,
            500,
            89,
            448,
            296,
            349,
            500,
            500,
            500,
            500,
            500,
            500,
            181,
            331,
            144,
            218,
            165,
            161,
            184,
            122,
            87,
            115,
            102,
            57,
            117,
            33,
            37,
            105,
            50,
            103,
            106,
            34,
            124,
            118,
            38,
            115,
            118,
            110,
            115,
            113,
            88,
            116,
            128,
            99,
            141,
            162,
            148,
            304,
            152,
            209,
            118,
            185,
            168,
            220,
            500,
            500,
            95,
            347,
            270,
            177,
            234,
            415,
            137,
            233,
            500,
            366,
            477,
            500,
            108,
            317,
            500,
            500,
            405,
            500,
            500,
            500,
            500,
            150,
            180,
            340,
            129,
            311,
            184,
            269,
            46,
            146,
            92,
            95,
            192,
            141,
            162,
            141,
            250,
            131,
            100,
            171,
            177,
            136,
            137,
            140,
            55,
            75,
            41,
            100,
            79,
            131,
            93,
            132,
            120,
            124,
            145,
            132,
            113,
            124,
            69,
            157,
            119,
            124,
            153,
            173,
            148,
            148,
            171,
            161,
            157,
            169,
            188,
            158,
            197,
            210,
            445,
            319,
            500,
            495,
            500,
            420,
            438,
            354,
            305,
            369,
            372,
            347,
            286,
            272,
            182,
            243,
            149,
            206,
            230,
            230,
            224,
            259,
            175,
            156,
            230,
            171,
            204,
            168,
            142,
            128,
            140,
            145,
            137,
            135,
            105,
            129,
            161,
            128,
            122,
            128,
            46,
            113,
            139,
            114,
            156,
            153,
            172,
            144,
            98,
            176,
            194,
            188,
            166,
            208,
            181,
            210,
            212,
            202,
            188,
            179,
            195,
            197,
            181,
            189,
            231,
            215,
            216,
            217,
            241,
            202,
            258,
            218,
            235,
            326,
            263,
            245,
            373,
            328,
            270,
            353,
            293,
            500,
            500,
            227,
            288,
            384,
            308,
            293,
            324,
            281,
            338,
            285,
            366,
            264,
            284,
            281,
            329,
            208,
            249,
            187,
            217,
            268,
            217,
            280,
            297,
            220,
            252,
            256,
            243,
            296,
            219,
            317,
            454,
            438,
            332,
            500,
            500,
            500,
            500,
            500,
            500,
            259,
            331,
            388,
            148,
            167,
            315,
            148,
            311,
            124,
            152,
            381,
            287,
            235,
            500,
            343,
            181,
            280,
            500,
            122,
            328,
            298,
            260,
            300,
            128,
            190,
            157,
            403,
            311,
            500,
            483,
            250,
            500,
            500,
            500,
            500,
            500,
            500,
            500,
            500,
            500,
            500,
            500,
            500,
            500,
            500,
            500
        ],
        "episode_count": 1080,
        "average_timesteps_per_episode": 166.56296296296296,
        "episode_rewards_min": 8.0,
        "episode_rewards_max": 500.0,
        "episode_rewards_mean": 166.56296296296296,
        "episode_rewards_median": 130.0,
        "episode_rewards_std": 126.57810397551255,
        "episode_rewards_iqr": 139.0,
        "episode_rewards_q1": 78.0,
        "episode_rewards_q3": 217.0,
        "training_time": 10134.914031982422
    },
    "timings": {
        "overall_experiment_time": 10135.855175733566,
        "training_time": 10134.914031982422
    }
}